DESCRIPTION.rst
LICENSE.txt
MANIFEST.in
README.rst
VERSION
setup.py
prost/__init__.py
prost/__main__.py
prost/_version.py
prost/alignment.py
prost/annotation.py
prost/command_line.py
prost/common.py
prost/constants.py
prost/db_caching.py
prost/excel.PLAY.py
prost/excel.PLAY2.py
prost/excel.py
prost/prost.py
prost.egg-info/PKG-INFO
prost.egg-info/SOURCES.txt
prost.egg-info/dependency_links.txt
prost.egg-info/entry_points.txt
prost.egg-info/requires.txt
prost.egg-info/top_level.txt