Metadata-Version: 1.1
Name: prost
Version: 0.7.58
Summary: An application to quantify and annotate miRNA expression.
Home-page: https://github.com/uoregon-postlethwait/prost
Author: Jason Sydes and Peter Batzel
Author-email: sydes@uoregon.edu
License: LICENSE.txt
Keywords: bioinformatics microRNA miRNA miR
Platform: UNKNOWN
Classifier: Development Status :: 5 - Production/Stable
Classifier: Intended Audience :: Science/Research
Classifier: Topic :: Scientific/Engineering :: Bio-Informatics
Classifier: License :: Free for non-commercial use
Classifier: Programming Language :: Python :: 2
Classifier: Programming Language :: Python :: 2.7
